{"assets/banner.png":["assets/banner.png"],"assets/discord_logo.svg":["assets/discord_logo.svg"],"assets/flutterkaigi-navbar_dark_logo.svg":["assets/flutterkaigi-navbar_dark_logo.svg"],"assets/flutterkaigi-navbar_light_logo.svg":["assets/flutterkaigi-navbar_light_logo.svg"],"assets/flutterkaigi_logo.svg":["assets/flutterkaigi_logo.svg"],"assets/github_logo.svg":["assets/github_logo.svg"],"assets/medium_logo.svg":["assets/medium_logo.svg"],"assets/photo/katsummy.png":["assets/photo/katsummy.png"],"assets/sponsor/autify.svg":["assets/sponsor/autify.svg"],"assets/sponsor/chompy.svg":["assets/sponsor/chompy.svg"],"assets/sponsor/compass.svg":["assets/sponsor/compass.svg"],"assets/sponsor/cyber_agent.svg":["assets/sponsor/cyber_agent.svg"],"assets/sponsor/demaecan.svg":["assets/sponsor/demaecan.svg"],"assets/sponsor/dena.svg":["assets/sponsor/dena.svg"],"assets/sponsor/diverse.svg":["assets/sponsor/diverse.svg"],"assets/sponsor/enechain.svg":["assets/sponsor/enechain.svg"],"assets/sponsor/excite.svg":["assets/sponsor/excite.svg"],"assets/sponsor/fastdoctor.svg":["assets/sponsor/fastdoctor.svg"],"assets/sponsor/hokuto.svg":["assets/sponsor/hokuto.svg"],"assets/sponsor/layerx.svg":["assets/sponsor/layerx.svg"],"assets/sponsor/m3.svg":["assets/sponsor/m3.svg"],"assets/sponsor/studyplus.svg":["assets/sponsor/studyplus.svg"],"assets/sponsor/tenx.svg":["assets/sponsor/tenx.svg"],"assets/sponsor/tokyu.svg":["assets/sponsor/tokyu.svg"],"assets/sponsor/youtrust.svg":["assets/sponsor/youtrust.svg"],"assets/sponsor/yumemi.svg":["assets/sponsor/yumemi.svg"],"assets/twitter_logo.svg":["assets/twitter_logo.svg"],"assets/twitter_white.svg":["assets/twitter_white.svg"],"packages/cupertino_icons/assets/CupertinoIcons.ttf":["packages/cupertino_icons/assets/CupertinoIcons.ttf"]}